pycleaner/__init__.py
pycleaner/clean.py
pycleaner-1.1.2.dist-info/METADATA
pycleaner-1.1.2.dist-info/WHEEL
pycleaner-1.1.2.dist-info/entry_points.txt
pycleaner-1.1.2.dist-info/top_level.txt
pycleaner-1.1.2.dist-info/RECORD
