Metadata-Version: 2.1
Name: pycleaner
Version: 1.1.2
Summary: Remove ~ and .pyc recursively
Home-page: UNKNOWN
Author: Michael Carter
Author-email: CarterMichael@gmail.com
License: MIT License
Platform: UNKNOWN
Classifier: Development Status :: 3 - Alpha
Classifier: Environment :: Console
Classifier: Intended Audience :: Developers
Classifier: License :: OSI Approved :: MIT License
Classifier: Operating System :: OS Independent
Classifier: Programming Language :: Python
Classifier: Topic :: Software Development :: Libraries :: Python Modules
